netatmoqc/__init__.py
netatmoqc/apps/LICENSE.md
netatmoqc/apps/clustering/__init__.py
netatmoqc/apps/clustering/app.py
netatmoqc/apps/clustering/assets/Acumin-BdPro.otf
netatmoqc/apps/clustering/assets/base.css
netatmoqc/apps/clustering/assets/clinical-analytics.css
netatmoqc/apps/clustering/assets/indicators.css
netatmoqc/apps/clustering/assets/plotly_logo.png
netatmoqc/apps/clustering/assets/resizing.js
netatmoqc/apps/scattergeo_timeseries/Procfile
netatmoqc/apps/scattergeo_timeseries/README.md
netatmoqc/apps/scattergeo_timeseries/__init__.py
netatmoqc/apps/scattergeo_timeseries/app.py
netatmoqc/apps/scattergeo_timeseries/assets/Acumin-BdPro.otf
netatmoqc/apps/scattergeo_timeseries/assets/base.css
netatmoqc/apps/scattergeo_timeseries/assets/clinical-analytics.css
netatmoqc/apps/scattergeo_timeseries/assets/plotly_logo.png
netatmoqc/apps/scattergeo_timeseries/assets/resizing.js
netatmoqc/apps/scattergeo_timeseries/requirements.txt
netatmoqc/apps/server.py
netatmoqc/apps/wsgi.py
netatmoqc/argparse_wrapper.py
netatmoqc/bin/start_apps
netatmoqc/clustering.py
netatmoqc/commands_functions.py
netatmoqc/config_parser.py
netatmoqc/domains.py
netatmoqc/dtgs.py
netatmoqc/hollow_symmetric_matrix.py
netatmoqc/load_data.py
netatmoqc/logs.py
netatmoqc/main.py
netatmoqc/metrics.py
netatmoqc/mpi.py
netatmoqc/outlier_removal.py
netatmoqc/plots.py
netatmoqc/save_data.py
netatmoqc-0.3.9.dist-info/entry_points.txt
netatmoqc-0.3.9.dist-info/LICENSE.md
netatmoqc-0.3.9.dist-info/WHEEL
netatmoqc-0.3.9.dist-info/METADATA
netatmoqc-0.3.9.dist-info/RECORD
