Metadata-Version: 2.1
Name: netatmoqc
Version: 0.3.9
Summary: Use machine learning clustering methods to perform quality control over NetAtmo data
Home-page: https://source.coderefinery.org/iOBS/wp2/task-2-3/netatmoqc
License: MIT
Author: Paulo V. C. Medeiros
Author-email: paulo.medeiros@smhi.se
Requires-Python: >=3.8.8,<3.10
Classifier: License :: OSI Approved :: MIT License
Classifier: Programming Language :: Python :: 3
Classifier: Programming Language :: Python :: 3.9
Provides-Extra: mpi
Requires-Dist: attrs (>=21.2.0,<22.0.0)
Requires-Dist: dash (>=1.13.4,<2.0.0)
Requires-Dist: dash-daq (>=0.5.0,<0.6.0)
Requires-Dist: dotmap (>=1.3.17,<2.0.0)
Requires-Dist: flask-caching (>=1.9.0,<2.0.0)
Requires-Dist: hdbscan (>=0.8.26,<0.9.0)
Requires-Dist: humanize (>=3.7.0,<4.0.0)
Requires-Dist: importlib-metadata (>=4.5.0,<5.0.0)
Requires-Dist: joblib (>=1.0.0,<2.0.0)
Requires-Dist: llvmlite (==0.36.0)
Requires-Dist: mpi4py (>=3.0.3,<4.0.0); extra == "mpi"
Requires-Dist: numba (>=0.53.1,<0.54.0)
Requires-Dist: numpy (>=1.19.0,<2.0.0)
Requires-Dist: pandas (>=1.2.4,<2.0.0)
Requires-Dist: plotly (>=4.8.2,<5.0.0)
Requires-Dist: psutil (>=5.7.0,<6.0.0)
Requires-Dist: pyproj (>=3.1.0,<4.0.0)
Requires-Dist: pytz (>=2021.1,<2022.0)
Requires-Dist: redis (>=3.5.3,<4.0.0)
Requires-Dist: scikit-learn (>=0.24.2,<0.25.0)
Requires-Dist: tbb (>=2021.2.0,<2022.0.0); sys_platform != "darwin"
Requires-Dist: toml (>=0.10.1,<0.11.0)
Project-URL: Documentation, https://source.coderefinery.org/iOBS/wp2/task-2-3/netatmoqc/-/wikis
Project-URL: Repository, https://source.coderefinery.org/iOBS/wp2/task-2-3/netatmoqc
